discounts_pkg/__init__.py
discounts_pkg/discounts.py
discounts_pkg-0.0.4.dist-info/METADATA
discounts_pkg-0.0.4.dist-info/WHEEL
discounts_pkg-0.0.4.dist-info/licenses/LICENSE
discounts_pkg-0.0.4.dist-info/RECORD
