Metadata-Version: 2.3
Name: discounts_pkg
Version: 0.0.4
Summary: A library to apply discounts on your products or services.
Project-URL: Homepage, https://github.com/pypa/sampleproject
Project-URL: Bug Tracker, https://github.com/pypa/sampleproject/issues
Author-email: Muhammad Arsil Khan <arsil.36k@gmail.com>
Classifier: License :: OSI Approved :: MIT License
Classifier: Operating System :: OS Independent
Classifier: Programming Language :: Python :: 3
Requires-Python: >=3.7
